ml_helper/__init__.py
ml_helper/helper.py
ml_helper-0.0.23.dist-info/METADATA
ml_helper-0.0.23.dist-info/WHEEL
ml_helper-0.0.23.dist-info/license.txt
ml_helper-0.0.23.dist-info/top_level.txt
ml_helper-0.0.23.dist-info/RECORD
